miniweb/__init__.py
miniweb/core.py
miniweb/exceptions.py
miniweb/middlewares.py
miniweb/request.py
miniweb/response.py
miniweb/router.py
miniweb/sapi.py
miniweb/server.py
miniweb/contrib/__init__.py
miniweb/contrib/static_files.py
miniweb-0.1.15.dist-info/licenses/LICENSE
miniweb-0.1.15.dist-info/METADATA
miniweb-0.1.15.dist-info/WHEEL
miniweb-0.1.15.dist-info/top_level.txt
miniweb-0.1.15.dist-info/RECORD
