Metadata-Version: 2.4
Name: miniweb
Version: 0.1.15
Summary: A simple web framework for Python.
Author: rRR0VrFP
Maintainer: rRR0VrFP
License: MIT
Keywords: miniweb
Classifier: Development Status :: 5 - Production/Stable
Classifier: Intended Audience :: Developers
Classifier: Topic :: Software Development :: Libraries :: Python Modules
Classifier: License :: OSI Approved :: MIT License
Classifier: Programming Language :: Python :: 3
Classifier: Programming Language :: Python :: 3 :: Only
License-File: LICENSE
Requires-Dist: bizerror
Requires-Dist: fastutils>=0.42.6
Requires-Dist: cached-property
Dynamic: author
Dynamic: classifier
Dynamic: description
Dynamic: description-content-type
Dynamic: keywords
Dynamic: license
Dynamic: license-file
Dynamic: maintainer
Dynamic: requires-dist
Dynamic: summary
